zaber_motion_bindings_darwin/__init__.py
zaber_motion_bindings_darwin/bindings.py
zaber_motion_bindings_darwin/version.py
zaber_motion_bindings_darwin/zaber-motion-lib-darwin-uni.dylib
zaber_motion_bindings_darwin-5.1.1.dist-info/LICENSE.txt
zaber_motion_bindings_darwin-5.1.1.dist-info/METADATA
zaber_motion_bindings_darwin-5.1.1.dist-info/WHEEL
zaber_motion_bindings_darwin-5.1.1.dist-info/top_level.txt
zaber_motion_bindings_darwin-5.1.1.dist-info/RECORD
