Metadata-Version: 2.1
Name: zaber_motion_bindings_darwin
Version: 5.1.1
Summary: Mac OS bindings for Zaber Motion Library
Home-page: https://gitlab.com/ZaberTech/zaber-motion-lib
Author: Zaber Technologies Inc.
Author-email: contact@zaber.com
License: MIT
Classifier: Development Status :: 5 - Production/Stable
Classifier: Intended Audience :: Developers
Classifier: Topic :: Software Development :: Libraries
License-File: LICENSE.txt
Provides-Extra: build
Requires-Dist: invoke ; extra == 'build'
